LICENSE.txt
MANIFEST.in
README.rst
setup.py
colormath/__init__.py
colormath/color_constants.py
colormath/color_conversions.py
colormath/color_diff.py
colormath/color_diff_matrix.py
colormath/color_exceptions.py
colormath/color_objects.py
colormath/density.py
colormath/density_standards.py
colormath/spectral_constants.py
colormath.egg-info/PKG-INFO
colormath.egg-info/SOURCES.txt
colormath.egg-info/dependency_links.txt
colormath.egg-info/top_level.txt
examples/conversions.py
examples/delta_e.py
examples/delta_e_matrix.py
examples/density.py
examples/example_config.py