Metadata-Version: 1.1
Name: colormath
Version: 1.0.9
Summary: Color math and conversion library.
Home-page: http://code.google.com/p/python-colormath/
Author: Gregory Taylor
Author-email: gtaylor@l11solutions.com
License: BSD
Download-URL: http://pypi.python.org/pypi/colormath/
Keywords: color math conversions
Platform: Platform Independent
Classifier: Development Status :: 5 - Production/Stable
Classifier: Intended Audience :: Developers
Classifier: License :: OSI Approved :: BSD License
Classifier: Natural Language :: English
Classifier: Operating System :: OS Independent
Classifier: Programming Language :: Python
Classifier: Topic :: Scientific/Engineering :: Mathematics
Classifier: Topic :: Software Development :: Libraries :: Python Modules
Requires: numpy
